scaden/__init__.py
scaden/__main__.py
scaden/example.py
scaden/merge.py
scaden/predict.py
scaden/process.py
scaden/simulate.py
scaden/train.py
scaden/model/__init__.py
scaden/model/architectures.py
scaden/model/functions.py
scaden/model/scaden.py
scaden/simulation/__init__.py
scaden/simulation/bulk_simulator.py
scaden-1.1.2.dist-info/LICENSE
scaden-1.1.2.dist-info/METADATA
scaden-1.1.2.dist-info/WHEEL
scaden-1.1.2.dist-info/entry_points.txt
scaden-1.1.2.dist-info/top_level.txt
scaden-1.1.2.dist-info/RECORD
