Metadata-Version: 2.1
Name: scaden
Version: 1.1.2
Summary: Cell type deconvolution using single cell data
Home-page: https://github.com/KevinMenden/scaden
Author: Kevin Menden
Author-email: kevin.menden@t-online.de
License: MIT License
Keywords: bioinformatics,deep learning,machine learning,single cell sequencing,deconvolution
Platform: UNKNOWN
Requires-Python: >3.6.0
License-File: LICENSE
Requires-Dist: pandas
Requires-Dist: numpy
Requires-Dist: scikit-learn
Requires-Dist: tensorflow (>=2.0)
Requires-Dist: anndata
Requires-Dist: click
Requires-Dist: h5py
Requires-Dist: rich
